{
  "project_info": {
    "project_number": "531046758556",
    "firebase_url": "https://adwin-client-backend-default-rtdb.firebaseio.com",
    "project_id": "adwin-client-backend",
    "storage_bucket": "adwin-client-backend.appspot.com"
  },
  "client": [
    {
      "client_info": {
        "mobilesdk_app_id": "1:531046758556:android:ebdac638a0289558ebd559",
        "android_client_info": {
          "package_name": "com.example.adwindow.adwindow_client"
        }
      },
      "oauth_client": [
        {
          "client_id": "531046758556-ic0dsm7o5k2mqk2uclk40gtpd5tbau1b.apps.googleusercontent.com",
          "client_type": 1,
          "android_info": {
            "package_name": "com.example.adwindow.adwindow_client",
            "certificate_hash": "9eac7da0f426ac7af20b2c35867e40468dd38a7e"
          }
        },
        {
          "client_id": "531046758556-nakv4hg1nem20grrvh1ote2cnmpi5moj.apps.googleusercontent.com",
          "client_type": 3
        }
      ],
      "api_key": [
        {
          "current_key": "AIzaSyC6Iy1lZ25xhF0z6hWrfrHHEDNHP1Mrcw4"
        }
      ],
      "services": {
        "appinvite_service": {
          "other_platform_oauth_client": [
            {
              "client_id": "531046758556-nakv4hg1nem20grrvh1ote2cnmpi5moj.apps.googleusercontent.com",
              "client_type": 3
            }
          ]
        }
      }
    }
  ],
  "configuration_version": "1"
}